SimonControl.v
//==============================================================================
// Control Module for Simon Project
//==============================================================================

module SimonControl(
	// External Inputs
	input        clk,           // Clock
	input        rst,           // Reset

	// Datapath Inputs
	input     index_lt_count,
	input 	  pattern_eq_mem,
	input 	  pattern_valid,

	// Datapath Control Outputs
	output    reg count_cnt,
	output	  reg count_clr,
	output	  reg index_cnt,
	output 	  reg index_clr,
	output 	  reg disp_mem,
	output 	  reg w_en,
	output 	  reg load_level,
	// External Outputs
	output reg [2:0] mode_leds
);

	// Declare Local Vars Here
	reg [1:0] state;
	reg [1:0] next_state;

	// LED Light Parameters
	localparam LED_MODE_INPUT    = 3'b001;
	localparam LED_MODE_PLAYBACK = 3'b010;
	localparam LED_MODE_REPEAT   = 3'b100;
	localparam LED_MODE_DONE     = 3'b111;

	// Declare State Names Here
	localparam STATE_INPUT = 2'd0;
	localparam STATE_PLAYBACK = 2'd1;
	localparam STATE_REPEAT = 2'd2;
	localparam STATE_DONE = 2'd3;

	// Output Combinational Logic
	always @( * ) begin

		count_clr <= rst;
		load_level <= rst;
		count_cnt <= 0;
		index_cnt <= 0;
		index_clr <= 0;
		disp_mem <= 0;
		w_en <= 0;
		mode_leds <= 3'd0;

		case (state)
		  STATE_INPUT: begin
			mode_leds <= LED_MODE_INPUT;
			w_en <= pattern_valid;
			index_clr <= pattern_valid;
		  end
		  STATE_PLAYBACK: begin
			mode_leds <= LED_MODE_PLAYBACK;
			disp_mem <= 1;
			index_cnt <= index_lt_count;
			index_clr <= !index_lt_count;
		  end
		  STATE_REPEAT: begin
			mode_leds <= LED_MODE_REPEAT;
			index_cnt <= index_lt_count & pattern_eq_mem;
			index_clr <= !pattern_eq_mem;
			count_cnt <= !index_lt_count & pattern_eq_mem;
		  end
		  STATE_DONE: begin
			mode_leds <= LED_MODE_DONE;
			disp_mem <= 1;
			index_cnt <= index_lt_count;
			index_clr <= !index_lt_count;
		  end
		endcase


	end

	// Next State Combinational Logic
	always @( * ) begin

		case (state)
		  STATE_INPUT: begin
			if (!pattern_valid) next_state = STATE_INPUT;
			else next_state = STATE_PLAYBACK;
		  end
		  STATE_PLAYBACK: begin
			if (index_lt_count) next_state = STATE_PLAYBACK;
			else next_state = STATE_REPEAT;
		  end
		  STATE_REPEAT: begin
			if (index_lt_count & pattern_eq_mem) next_state = STATE_REPEAT;
			else if (!index_lt_count & pattern_eq_mem) next_state = STATE_INPUT;
			else next_state = STATE_DONE;
		  end
		  STATE_DONE: begin
			next_state = STATE_DONE;
		  end
		endcase	

	end

	// State Update Sequential Logic
	always @(posedge clk) begin
		if (rst) begin
			// Update state to reset state
			state <= STATE_INPUT;
		end
		else begin
			// Update state to next state
			state <= next_state;
		end
	end

endmodule

SimonControl.t.v
//===============================================================================
// Testbench Module for Simon Controller
//===============================================================================
`timescale 1ns/100ps

`include "SimonControl.v"

// Print an error message (MSG) if value ONE is not equal
// to value TWO.
`define ASSERT_EQ(ONE, TWO, MSG)               \
	begin                                      \
		if ((ONE) !== (TWO)) begin             \
			$display("\t[FAILURE]:%s", (MSG)); \
		end                                    \
	end #0

// Set the variable VAR to the value VALUE, printing a notification
// to the screen indicating the variable's update.
// The setting of the variable is preceeded and followed by
// a 1-timestep delay.
`define SET(VAR, VALUE) $display("Setting %s to %s...", "VAR", "VALUE"); #1; VAR = (VALUE); #1

// Cycle the clock up and then down, simulating
// a button press.
`define CLOCK $display("Pressing uclk..."); #1; clk = 1; #1; clk = 0; #1

module SimonControlTest;

	// Local Vars
	reg clk = 0;
	reg rst = 0;
	reg pattern_valid = 0;
	reg index_lt_count = 0;
	reg pattern_eq_mem = 0;
	wire count_cnt, count_clr, index_cnt, index_clr, disp_mem, w_en, load_level;
	wire [2:0] mode_leds;


	// LED Light Parameters
	localparam LED_MODE_INPUT    = 3'b001;
	localparam LED_MODE_PLAYBACK = 3'b010;
	localparam LED_MODE_REPEAT   = 3'b100;
	localparam LED_MODE_DONE     = 3'b111;

	// VCD Dump
	initial begin
		$dumpfile("SimonControlTest.vcd");
		$dumpvars;
	end

	// Simon Control Module
	SimonControl ctrl(
		.clk (clk),
		.rst (rst),
		.index_lt_count (index_lt_count),
		.pattern_eq_mem (pattern_eq_mem),
		.pattern_valid (pattern_valid),
		.count_cnt(count_cnt),
		.count_clr(count_clr),
		.index_clr(index_clr),
		.index_cnt(index_cnt),
		.disp_mem(disp_mem),
		.w_en(w_en),
		.load_level(load_level),
		.mode_leds(mode_leds)
	);

	// Main Test Logic
	initial begin
		// Reset the game
		`SET(rst, 1);
		`ASSERT_EQ(count_clr,1,"Count not cleared on reset");
		`ASSERT_EQ(load_level, 1, "Level load not 1 on reset");
		`CLOCK;
		`SET(rst, 0);
		`ASSERT_EQ(count_clr,0,"Count clear not 0");
		`ASSERT_EQ(load_level, 0, "Level load not 0");
		`ASSERT_EQ(mode_leds, LED_MODE_INPUT, "Wrong mode");

		`SET(pattern_valid, 1);
		`ASSERT_EQ(w_en, 1 , "write enable when valid pattern");
		`ASSERT_EQ(index_clr, 1, "clear index when valid pattern");
		`ASSERT_EQ(disp_mem, 0, "displaying pattern in input mode");
		
		`CLOCK;

		`SET(pattern_valid, 0);
		`ASSERT_EQ(mode_leds, LED_MODE_PLAYBACK, "mode not in playback");
		`ASSERT_EQ(disp_mem, 1, "playback not displaying mem");
		
		`SET(index_lt_count, 1)

		`ASSERT_EQ(index_cnt, 1, "not incrementing index");
		`ASSERT_EQ(index_clr, 0, "clearing index too soon");

		`CLOCK;
		`ASSERT_EQ(mode_leds, LED_MODE_PLAYBACK, "mode didn't stay in playback");

		`SET(index_lt_count, 0);
		`CLOCK;

		`SET(index_lt_count, 0);
		`SET(pattern_eq_mem, 1);

		`ASSERT_EQ(mode_leds, LED_MODE_REPEAT, "mode not in repeat");
		`ASSERT_EQ(disp_mem, 0, "not displaying switches");
		`ASSERT_EQ(index_clr, 0, "clearing without being done");
		`ASSERT_EQ(count_cnt, 1, "not incrementing count");

		`CLOCK;
		`ASSERT_EQ(mode_leds, LED_MODE_INPUT, "Did not go into input mode");	

		`SET(pattern_valid,0);
		`ASSERT_EQ(w_en, 0, "writing incorrect pattern");
		`ASSERT_EQ(disp_mem, 0, "not displaying pattern");

		`CLOCK;
		`ASSERT_EQ(mode_leds, LED_MODE_INPUT, "advanced to playback without correct pattern");

		`SET(pattern_valid, 1);
		`CLOCK;
		`SET(index_lt_count, 0);
		`CLOCK;

		`ASSERT_EQ(mode_leds, LED_MODE_REPEAT, "Mode not in repeat");

		`SET(pattern_eq_mem, 0);
		`CLOCK;
		`ASSERT_EQ(mode_leds, LED_MODE_DONE, "Mode not done after incorrect pattern");

		$finish;
	end

endmodule

SimonControlTest.vcd
$date
	Fri Nov 17 17:58:15 2017
$end
$version
	Icarus Verilog
$end
$timescale
	100ps
$end
$scope module SimonControlTest $end
$var wire 1 ! w_en $end
$var wire 3 " mode_leds [2:0] $end
$var wire 1 # load_level $end
$var wire 1 $ index_cnt $end
$var wire 1 % index_clr $end
$var wire 1 & disp_mem $end
$var wire 1 ' count_cnt $end
$var wire 1 ( count_clr $end
$var reg 1 ) clk $end
$var reg 1 * index_lt_count $end
$var reg 1 + pattern_eq_mem $end
$var reg 1 , pattern_valid $end
$var reg 1 - rst $end
$scope module ctrl $end
$var wire 1 ) clk $end
$var wire 1 * index_lt_count $end
$var wire 1 + pattern_eq_mem $end
$var wire 1 , pattern_valid $end
$var wire 1 - rst $end
$var reg 1 ( count_clr $end
$var reg 1 ' count_cnt $end
$var reg 1 & disp_mem $end
$var reg 1 % index_clr $end
$var reg 1 $ index_cnt $end
$var reg 1 # load_level $end
$var reg 3 . mode_leds [2:0] $end
$var reg 2 / next_state [1:0] $end
$var reg 2 0 state [1:0] $end
$var reg 1 ! w_en $end
$upscope $end
$upscope $end
$enddefinitions $end
#0
$dumpvars
bx 0
bx /
b0 .
0-
0,
0+
0*
0)
0(
0'
0&
0%
0$
0#
b0 "
0!
$end
#10
1#
1(
1-
#30
b1 "
b1 .
b0 /
b0 0
1)
#40
0)
#60
b1 "
b1 .
0#
0(
0-
#80
1%
1!
b1 "
b1 .
b1 /
1,
#100
1&
b10 "
b10 .
0!
1%
b10 /
b1 0
1)
#110
0)
#130
b10 "
b10 .
1&
1%
0,
#150
1$
b10 "
b10 .
1&
0%
b1 /
1*
#170
1)
#180
0)
#200
1%
b10 "
b10 .
1&
0$
b10 /
0*
#220
b100 "
b100 .
0&
1%
b11 /
b10 0
1)
#230
0)
#270
1'
b100 "
b100 .
0%
b0 /
1+
#290
b1 "
b1 .
0'
b0 0
1)
#300
0)
#340
1)
#350
0)
#370
1%
1!
b1 "
b1 .
b1 /
1,
#390
1&
b10 "
b10 .
0!
1%
b10 /
b1 0
1)
#400
0)
#440
1'
b100 "
b100 .
0&
0%
b0 /
b10 0
1)
#450
0)
#470
1%
b100 "
b100 .
0'
b11 /
0+
#490
1&
b111 "
b111 .
1%
b11 0
1)
